{
  "info": {
    "app_id": "com.makeawesomehappen.pebblemars",
    "app_uuid": "75A4956D-EDD0-48B1-89F8-68B88813BB22",
    "app_name": "Pebble Mars",
    "support_url": "http://www.getpebble.com",
    "version_label": "1.0.1",
    "version_code": 1,
    "app_key_type": "manual"
  },
  "app_keys": {
     "icon": 0,
     "temperature":1,
     "rel_time": 2,
     "instrument": 3,
     "utc": 4,
     "filename": 5,
     "image_start": 419,
     "image_index": 420,
     "image_data": 421,
     "image_complete": 422,
     "image_request_chunk": 423,
     "image_request_next": 424
  }
}
